tendon/__init__.py
tendon/api/__init__.py
tendon/api/context.py
tendon/api/node.py
tendon/api/nodes/__init__.py
tendon/api/nodes/application.py
tendon/api/nodes/application_request.py
tendon/api/nodes/chat_channel.py
tendon/api/nodes/client_profile_invitation.py
tendon/api/nodes/image.py
tendon/api/nodes/program.py
tendon/api/nodes/program_invitation.py
tendon/api/nodes/program_module.py
tendon/api/nodes/program_track_action.py
tendon/api/nodes/program_track_action_response.py
tendon/api/nodes/program_track_event.py
tendon/api/nodes/session.py
tendon/api/nodes/tag.py
tendon/api/nodes/user.py
tendon/api/obschart_api_client.py
tendon/application_request_handler.py
tendon/blocks_action_builder.py
tendon/extract_files.py
tendon/gql/__init__.py
tendon/gql/gql.py
tendon/gql/gql_client.py
tendon/gql/gql_client_transport.py
tendon/obschart_api_transport.py
tendon/obschart_client.py
tendon/py.typed
tendon/step_builder.py
tendon-1.2.0.dist-info/WHEEL
tendon-1.2.0.dist-info/METADATA
tendon-1.2.0.dist-info/RECORD
