Metadata-Version: 2.1
Name: tendon
Version: 1.2.0
Summary: 
Author: Tendon
Author-email: alastair@tendon.io
Requires-Python: >=3.6,<4.0
Classifier: Programming Language :: Python :: 3
Classifier: Programming Language :: Python :: 3.6
Classifier: Programming Language :: Python :: 3.7
Classifier: Programming Language :: Python :: 3.8
Requires-Dist: graphql-core (>=3.0.3,<4.0.0)
Requires-Dist: httpx (>=0.12.1,<0.13.0)
